LICENSE.txt
README.rst
setup.py
justml/__init__.py
justml/api.py
justml/estimator.py
justml/utils.py