Metadata-Version: 1.1
Name: justml
Version: 1.0.0
Summary: JustML client library
Home-page: https://justml.io
Author: JustML
Author-email: hello@justml.io
License: UNKNOWN
Keywords: justml ml machinelearning datascience
Platform: UNKNOWN
Classifier: Development Status :: 3 - Alpha
Classifier: Intended Audience :: Developers
Classifier: Topic :: Software Development :: Libraries :: Python Modules
Classifier: License :: OSI Approved :: MIT License
Classifier: Programming Language :: Python :: 2
Classifier: Programming Language :: Python :: 3
